pyparak/__init__.py
pyparak-0.0.4.dist-info/METADATA
pyparak-0.0.4.dist-info/WHEEL
pyparak-0.0.4.dist-info/top_level.txt
pyparak-0.0.4.dist-info/RECORD
