Metadata-Version: 2.1
Name: pyparak
Version: 0.0.4
Summary: A library which provides drivers for connecting to SHAPARAK gateways through single interface.
Home-page: https://github.com/mrdaliri/pyparak
Author: Mohammad-Reza Daliri
Author-email: rmdaliri@gmail.com
License: MIT
Platform: UNKNOWN
